LICENSE
MANIFEST.in
README.md
setup.cfg
setup.py
podiant_template_mail.egg-info/PKG-INFO
podiant_template_mail.egg-info/SOURCES.txt
podiant_template_mail.egg-info/dependency_links.txt
podiant_template_mail.egg-info/not-zip-safe
podiant_template_mail.egg-info/requires.txt
podiant_template_mail.egg-info/top_level.txt
template_mail/__init__.py
template_mail/context.py
template_mail/exceptions.py
template_mail/models.py
template_mail/settings.py
template_mail/tasks.py
template_mail/urls.py
template_mail/views.py
template_mail/migrations/0001_initial.py
template_mail/migrations/__init__.py
template_mail/templates/email/base.html
template_mail/templates/email/base.txt
template_mail/templates/email/tag.html