Metadata-Version: 2.1
Name: podiant-template-mail
Version: 0.2.1
Summary: A helper library for asynchronously sending HTML emails written in Markdown
Home-page: https://git.steadman.io/podiant/template-mail
Author: Mark Steadman
Author-email: mark@podiant.co
License: MIT
Keywords: podiant-template-mail
Platform: UNKNOWN
Classifier: Development Status :: 3 - Alpha
Classifier: Framework :: Django :: 1.11
Classifier: Intended Audience :: Developers
Classifier: License :: OSI Approved :: BSD License
Classifier: Natural Language :: English
Classifier: Programming Language :: Python :: 3
Classifier: Programming Language :: Python :: 3.4
Classifier: Programming Language :: Python :: 3.5
Classifier: Programming Language :: Python :: 3.6
